hypixel/__init__.py
hypixel/achievement.py
hypixel/aliases.py
hypixel/client.py
hypixel/color.py
hypixel/errors.py
hypixel/game.py
hypixel/py.typed
hypixel/utils.py
hypixel/models/__init__.py
hypixel/models/aliases.py
hypixel/models/bans.py
hypixel/models/friend.py
hypixel/models/games.py
hypixel/models/guild.py
hypixel/models/key.py
hypixel/models/leaderboards.py
hypixel/models/status.py
hypixel/models/utils.py
hypixel/models/player/__init__.py
hypixel/models/player/aliases.py
hypixel/models/player/arcade.py
hypixel/models/player/bedwars.py
hypixel/models/player/blitz.py
hypixel/models/player/duels.py
hypixel/models/player/murder_mystery.py
hypixel/models/player/paintball.py
hypixel/models/player/parkour.py
hypixel/models/player/player.py
hypixel/models/player/skywars.py
hypixel/models/player/socials.py
hypixel/models/player/tkr.py
hypixel/models/player/tnt_games.py
hypixel/models/player/uhc.py
hypixel/models/player/utils.py
hypixel/models/player/wool_games.py
hypixel.py-0.4.2.dist-info/LICENSE
hypixel.py-0.4.2.dist-info/METADATA
hypixel.py-0.4.2.dist-info/WHEEL
hypixel.py-0.4.2.dist-info/top_level.txt
hypixel.py-0.4.2.dist-info/RECORD
