Metadata-Version: 2.1
Name: hypixel.py
Version: 0.4.2
Summary: A Python wrapper for the Hypixel API
Author: duhby
License: MIT License
Project-URL: Source, https://github.com/duhby/hypixel.py/
Project-URL: Changelog, https://github.com/duhby/hypixel.py/blob/master/CHANGELOG.md
Project-URL: Documentation, https://hypixelpy.rtfd.io
Project-URL: Bug Tracker, https://github.com/duhby/hypixel.py/issues/
Classifier: Development Status :: 4 - Beta
Classifier: Natural Language :: English
Classifier: Programming Language :: Python :: 3.8
Classifier: Programming Language :: Python :: 3.9
Classifier: Programming Language :: Python :: 3.10
Classifier: License :: OSI Approved :: MIT License
Classifier: Typing :: Typed
Requires-Python: >=3.8
Provides-Extra: docs
Provides-Extra: data
Provides-Extra: speed
Provides-Extra: test
License-File: LICENSE
